bonzai/__init__.py
bonzai/cli.py
bonzai/commands.py
bonzai/core.py
bonzai-0.1.3.dist-info/entry_points.txt
bonzai-0.1.3.dist-info/LICENSE
bonzai-0.1.3.dist-info/METADATA
bonzai-0.1.3.dist-info/WHEEL
bonzai-0.1.3.dist-info/RECORD
