Metadata-Version: 2.3
Name: bonzai
Version: 0.1.3
Summary: Python package and minimalist CLI tool for visualizing, saving, and navigating directory structures.
Author: abhi-pixel1
Author-email: bharadwaj.abhi.r@gmail.com
Requires-Python: >=3.7
Classifier: Programming Language :: Python :: 3
Classifier: Programming Language :: Python :: 3.7
Classifier: Programming Language :: Python :: 3.8
Classifier: Programming Language :: Python :: 3.9
Classifier: Programming Language :: Python :: 3.10
Classifier: Programming Language :: Python :: 3.11
Classifier: Programming Language :: Python :: 3.12
Classifier: Programming Language :: Python :: 3.13
Requires-Dist: click (>=8.1.8,<9.0.0)
Requires-Dist: colorama (>=0.4.6,<0.5.0)
